hciplot/__init__.py
hciplot/hciplot.py
hciplot-0.2.6.dist-info/LICENSE
hciplot-0.2.6.dist-info/METADATA
hciplot-0.2.6.dist-info/WHEEL
hciplot-0.2.6.dist-info/top_level.txt
hciplot-0.2.6.dist-info/RECORD
