Metadata-Version: 2.1
Name: hciplot
Version: 0.2.6
Summary: High-contrast Imaging Plotting library
Home-page: https://github.com/carlgogo/hciplot
Download-URL: https://github.com/carlgogo/hciplot/archive/refs/tags/v0.1.8.tar.gz
Author: Carlos Alberto Gomez Gonzalez, Valentin Christiaens
Author-email: valentinchrist@hotmail.com
License: MIT
Keywords: plotting,hci,package
Classifier: Development Status :: 4 - Beta
Classifier: Environment :: Console
Classifier: Intended Audience :: Science/Research
Classifier: Operating System :: MacOS :: MacOS X
Classifier: Operating System :: POSIX :: Linux
Classifier: Natural Language :: English
Classifier: License :: OSI Approved :: MIT License
Classifier: Programming Language :: Python
Classifier: Programming Language :: Python :: 3.7
Classifier: Topic :: Scientific/Engineering :: Astronomy
License-File: LICENSE
Requires-Dist: numpy
Requires-Dist: matplotlib >=3.7.0
Requires-Dist: holoviews
Requires-Dist: bokeh
Requires-Dist: panel
Requires-Dist: jinja2
